Workbook

Sheet Financials>

Sheet Data

Sheet HistoricalFS
B2: ="Historical Financials Statements - "& 'Data Sheet'!B1
B3: Years | C3: ='Data Sheet'!B16 | D3: ='Data Sheet'!C16 | E3: ='Data Sheet'!D16 | F3: ='Data Sheet'!E16 | G3: ='Data Sheet'!F16 | H3: ='Data Sheet'!G16 | I3: ='Data Sheet'!H16 | J3: ='Data Sheet'!I16 | ... L3: ='Data Sheet'!K16 | M3: LTM
A5: # | B5: Income Statement
B6: Sales | C6: =IFERROR('Data Sheet'!B17,0) | D6: =IFERROR('Data Sheet'!C17,0) | E6: =IFERROR('Data Sheet'!D17,0) | F6: =IFERROR('Data Sheet'!E17,0) | G6: =IFERROR('Data Sheet'!F17,0) | H6: =IFERROR('Data Sheet'!G17,0) | I6: =IFERROR('Data Sheet'!H17,0) | J6: =IFERROR('Data Sheet'!I17,0) | ... L6: =IFERROR('Data Sheet'!K17,0) | M6: =IFERROR(SUM('Data Sheet'!H42:K42),0)
B7: Sales Growth | C7: - | D7: =D6/C6-1 | E7: =E6/D6-1 | F7: =F6/E6-1 | G7: =G6/F6-1 | H7: =H6/G6-1 | I7: =I6/H6-1 | J7: =J6/I6-1 | K7: =K6/J6-1 | ... M7: =M6/L6-1
B9: COGS | C9: =IFERROR(SUM('Data Sheet'!B18,'Data Sheet'!B20:B22)-1*'Data Sheet'!B19,0) | D9: =IFERROR(SUM('Data Sheet'!C18,'Data Sheet'!C20:C22)-1*'Data Sheet'!C19,0) | E9: =IFERROR(SUM('Data Sheet'!D18,'Data Sheet'!D20:D22)-1*'Data Sheet'!D19,0) | F9: =IFERROR(SUM('Data Sheet'!E18,'Data Sheet'!E20:E22)-1*'Data Sheet'!E19,0) | G9: =IFERROR(SUM('Data Sheet'!F18,'Data Sheet'!F20:F22)-1*'Data Sheet'!F19,0) | H9: =IFERROR(SUM('Data Sheet'!G18,'Data Sheet'!G20:G22)-1*'Data Sheet'!G19,0) | I9: =IFERROR(SUM('Data Sheet'!H18,'Data Sheet'!H20:H22)-1*'Data Sheet'!H19,0) | J9: =IFERROR(SUM('Data Sheet'!I18,'Data Sheet'!I20:I22)-1*'Data Sheet'!I19,0) | ... L9: =IFERROR(SUM('Data Sheet'!K18,'Data Sheet'!K20:K22)-1*'Data Sheet'!K19,0) | M9: =IFERROR(SUM('Data Sheet'!H43:K43),0)
B10: COGS % sales | C10: =C9/C6 | D10: =D9/D6 | E10: =E9/E6 | F10: =F9/F6 | G10: =G9/G6 | H10: =H9/H6 | I10: =I9/I6 | J10: =J9/J6 | ... M10: =M9/M6
B12: Gross Profit | C12: =C6-C9 | D12: =D6-D9 | E12: =E6-E9 | F12: =F6-F9 | G12: =G6-G9 | H12: =H6-H9 | I12: =I6-I9 | J12: =J6-J9 | ... M12: =M6-M9
B13: Gross Margin | C13: =C12/C6 | D13: =D12/D6 | E13: =E12/E6 | F13: =F12/F6 | G13: =G12/G6 | H13: =H12/H6 | I13: =I12/I6 | J13: =J12/J6 | ... M13: =M12/M6
B15: Selling and General Expenses | C15: =IFERROR(SUM('Data Sheet'!B23:B24),0) | D15: =IFERROR(SUM('Data Sheet'!C23:C24),0) | E15: =IFERROR(SUM('Data Sheet'!D23:D24),0) | F15: =IFERROR(SUM('Data Sheet'!E23:E24),0) | G15: =IFERROR(SUM('Data Sheet'!F23:F24),0) | H15: =IFERROR(SUM('Data Sheet'!G23:G24),0) | I15: =IFERROR(SUM('Data Sheet'!H23:H24),0) | J15: =IFERROR(SUM('Data Sheet'!I23:I24),0) | ... L15: =IFERROR(SUM('Data Sheet'!K23:K24),0)
B16: S&G Exp % sales | C16: =C15/C6 | D16: =D15/D6 | E16: =E15/E6 | F16: =F15/F6 | G16: =G15/G6 | H16: =H15/H6 | I16: =I15/I6 | J16: =J15/J6 | ... M16: =M15/M6
B18: EBITDA | C18: =C12-C15 | D18: =D12-D15 | E18: =E12-E15 | F18: =F12-F15 | G18: =G12-G15 | H18: =H12-H15 | I18: =I12-I15 | J18: =J12-J15 | ... L18: =L12-L15 | M18: =IFERROR(SUM('Data Sheet'!H46:K46,'Data Sheet'!H48:K48,'Data Sheet'!H45:K45),0)
B19: EBITDA%sales | C19: =C18/C6 | D19: =D18/D6 | E19: =E18/E6 | F19: =F18/F6 | G19: =G18/G6 | H19: =H18/H6 | I19: =I18/I6 | J19: =J18/J6 | ... M19: =M18/M6
B21: Interest | C21: =IFERROR(SUM('Data Sheet'!B27),0) | D21: =IFERROR(SUM('Data Sheet'!C27),0) | E21: =IFERROR(SUM('Data Sheet'!D27),0) | F21: =IFERROR(SUM('Data Sheet'!E27),0) | G21: =IFERROR(SUM('Data Sheet'!F27),0) | H21: =IFERROR(SUM('Data Sheet'!G27),0) | I21: =IFERROR(SUM('Data Sheet'!H27),0) | J21: =IFERROR(SUM('Data Sheet'!I27),0) | ... L21: =IFERROR(SUM('Data Sheet'!K27),0) | M21: =IFERROR(SUM('Data Sheet'!H46:K46),0)
B22: Interest % sales | C22: =C21/C6 | D22: =D21/D6 | E22: =E21/E6 | F22: =F21/F6 | G22: =G21/G6 | H22: =H21/H6 | I22: =I21/I6 | J22: =J21/J6 | ... M22: =M21/M6
B24: Depreciation | C24: =IFERROR('Data Sheet'!B26,0) | D24: =IFERROR('Data Sheet'!C26,0) | E24: =IFERROR('Data Sheet'!D26,0) | F24: =IFERROR('Data Sheet'!E26,0) | G24: =IFERROR('Data Sheet'!F26,0) | H24: =IFERROR('Data Sheet'!G26,0) | I24: =IFERROR('Data Sheet'!H26,0) | J24: =IFERROR('Data Sheet'!I26,0) | ... L24: =IFERROR('Data Sheet'!K26,0) | M24: =IFERROR(SUM('Data Sheet'!H45:K45),0)
B25: Depreciation % sales | C25: =C24/C6 | D25: =D24/D6 | E25: =E24/E6 | F25: =F24/F6 | G25: =G24/G6 | H25: =H24/H6 | I25: =I24/I6 | J25: =J24/J6 | ... M25: =M24/M6
B27: Earnings Before Tax | C27: =IFERROR(SUM(C18,C21,C24),0) | D27: =IFERROR(SUM(D18,D21,D24),0) | E27: =IFERROR(SUM(E18,E21,E24),0) | F27: =IFERROR(SUM(F18,F21,F24),0) | G27: =IFERROR(SUM(G18,G21,G24),0) | H27: =IFERROR(SUM(H18,H21,H24),0) | I27: =IFERROR(SUM(I18,I21,I24),0) | J27: =IFERROR(SUM(J18,J21,J24),0) | ... M27: =IFERROR(SUM(M18,M21,M24),0)
B28: EBT%sales | C28: =C27/C6 | D28: =D27/D6 | E28: =E27/E6 | F28: =F27/F6 | G28: =G27/G6 | H28: =H27/H6 | I28: =I27/I6 | J28: =J27/J6 | ... M28: =M27/M6
B30: Tax | C30: =IFERROR('Data Sheet'!B29,0) | D30: =IFERROR('Data Sheet'!C29,0) | E30: =IFERROR('Data Sheet'!D29,0) | F30: =IFERROR('Data Sheet'!E29,0) | G30: =IFERROR('Data Sheet'!F29,0) | H30: =IFERROR('Data Sheet'!G29,0) | I30: =IFERROR('Data Sheet'!H29,0) | J30: =IFERROR('Data Sheet'!I29,0) | ... L30: =IFERROR('Data Sheet'!K29,0) | M30: =IFERROR(SUM('Data Sheet'!H48:K48),0)
B31: Effective Tax rate | C31: =C30/C27 | D31: =D30/D27 | E31: =E30/E27 | F31: =F30/F27 | G31: =G30/G27 | H31: =H30/H27 | I31: =I30/I27 | J31: =J30/J27 | ... M31: =M30/M27
B33: Net Profit | C33: =IFERROR(C27-C30,0) | D33: =IFERROR(D27-D30,0) | E33: =IFERROR(E27-E30,0) | F33: =IFERROR(F27-F30,0) | G33: =IFERROR(G27-G30,0) | H33: =IFERROR(H27-H30,0) | I33: =IFERROR(I27-I30,0) | J33: =IFERROR(J27-J30,0) | ... M33: =IFERROR(M27-M30,0)
B34: Net margin | C34: =C33/C6 | D34: =D33/D6 | E34: =E33/E6 | F34: =F33/F6 | G34: =G33/G6 | H34: =H33/H6 | I34: =I33/I6 | J34: =J33/J6 | ... M34: =M33/M6
B36: No of Equity Shares | C36: =IFERROR('Data Sheet'!B93,0) | D36: =IFERROR('Data Sheet'!C93,0) | E36: =IFERROR('Data Sheet'!D93,0) | F36: =IFERROR('Data Sheet'!E93,0) | G36: =IFERROR('Data Sheet'!F93,0) | H36: =IFERROR('Data Sheet'!G93,0) | I36: =IFERROR('Data Sheet'!H93,0) | J36: =IFERROR('Data Sheet'!I93,0) | ... M36: =IFERROR('Data Sheet'!L93,0)
B38: EPS | C38: =IFERROR(C33/C36,0) | D38: =IFERROR(D33/D36,0) | E38: =IFERROR(E33/E36,0) | F38: =IFERROR(F33/F36,0) | G38: =IFERROR(G33/G36,0) | H38: =IFERROR(H33/H36,0) | I38: =IFERROR(I33/I36,0) | J38: =IFERROR(J33/J36,0) | ... M38: =IFERROR(M33/M36,0)
B39: EPS Growth | D39: =IFERROR(D38/C38-1,0) | E39: =IFERROR(E38/D38-1,0) | F39: =IFERROR(F38/E38-1,0) | G39: =IFERROR(G38/F38-1,0) | H39: =IFERROR(H38/G38-1,0) | I39: =IFERROR(I38/H38-1,0) | J39: =IFERROR(J38/I38-1,0) | K39: =IFERROR(K38/J38-1,0) | ... M39: =IFERROR(M38/L38-1,0)
B41: Dividend per share | C41: =IFERROR('Data Sheet'!B31/HistoricalFS!C36,0) | D41: =IFERROR('Data Sheet'!C31/HistoricalFS!D36,0) | E41: =IFERROR('Data Sheet'!D31/HistoricalFS!E36,0) | F41: =IFERROR('Data Sheet'!E31/HistoricalFS!F36,0) | G41: =IFERROR('Data Sheet'!F31/HistoricalFS!G36,0) | H41: =IFERROR('Data Sheet'!G31/HistoricalFS!H36,0) | I41: =IFERROR('Data Sheet'!H31/HistoricalFS!I36,0) | J41: =IFERROR('Data Sheet'!I31/HistoricalFS!J36,0) | ... M41: =IFERROR('Data Sheet'!L31/HistoricalFS!M36,0)
B42: Dividend payout ratio | C42: =IFERROR(C41/C38,0) | D42: =IFERROR(D41/D38,0) | E42: =IFERROR(E41/E38,0) | F42: =IFERROR(F41/F38,0) | G42: =IFERROR(G41/G38,0) | H42: =IFERROR(H41/H38,0) | I42: =IFERROR(I41/I38,0) | J42: =IFERROR(J41/J38,0) | ... M42: =IFERROR(M41/M38,0)
B44: Retained Earnings | C44: =IFERROR(IF(C38>C41,1-D42,0),0) | D44: =IFERROR(IF(D38>D41,1-E42,0),0) | E44: =IFERROR(IF(E38>E41,1-F42,0),0) | F44: =IFERROR(IF(F38>F41,1-G42,0),0) | G44: =IFERROR(IF(G38>G41,1-H42,0),0) | H44: =IFERROR(IF(H38>H41,1-I42,0),0) | I44: =IFERROR(IF(I38>I41,1-J42,0),0) | J44: =IFERROR(IF(J38>J41,1-K42,0),0) | ... M44: =IFERROR(IF(M38>M41,1-N42,0),0)
A47: # | B47: Balance Sheet
B48: Equity Share Capital | C48: =IFERROR('Data Sheet'!B57,0) | D48: =IFERROR('Data Sheet'!C57,0) | E48: =IFERROR('Data Sheet'!D57,0) | F48: =IFERROR('Data Sheet'!E57,0) | G48: =IFERROR('Data Sheet'!F57,0) | H48: =IFERROR('Data Sheet'!G57,0) | I48: =IFERROR('Data Sheet'!H57,0) | J48: =IFERROR('Data Sheet'!I57,0) | ... L48: =IFERROR('Data Sheet'!K57,0)
B49: Reserves | C49: =IFERROR('Data Sheet'!B58,0) | D49: =IFERROR('Data Sheet'!C58,0) | E49: =IFERROR('Data Sheet'!D58,0) | F49: =IFERROR('Data Sheet'!E58,0) | G49: =IFERROR('Data Sheet'!F58,0) | H49: =IFERROR('Data Sheet'!G58,0) | I49: =IFERROR('Data Sheet'!H58,0) | J49: =IFERROR('Data Sheet'!I58,0) | ... L49: =IFERROR('Data Sheet'!K58,0)
B50: Borrowings | C50: =IFERROR('Data Sheet'!B59,0) | D50: =IFERROR('Data Sheet'!C59,0) | E50: =IFERROR('Data Sheet'!D59,0) | F50: =IFERROR('Data Sheet'!E59,0) | G50: =IFERROR('Data Sheet'!F59,0) | H50: =IFERROR('Data Sheet'!G59,0) | I50: =IFERROR('Data Sheet'!H59,0) | J50: =IFERROR('Data Sheet'!I59,0) | ... L50: =IFERROR('Data Sheet'!K59,0)
B51: Other Liabilities | C51: =IFERROR('Data Sheet'!B60,0) | D51: =IFERROR('Data Sheet'!C60,0) | E51: =IFERROR('Data Sheet'!D60,0) | F51: =IFERROR('Data Sheet'!E60,0) | G51: =IFERROR('Data Sheet'!F60,0) | H51: =IFERROR('Data Sheet'!G60,0) | I51: =IFERROR('Data Sheet'!H60,0) | J51: =IFERROR('Data Sheet'!I60,0) | ... L51: =IFERROR('Data Sheet'!K60,0)
B52: Total Liablities | C52: =IFERROR('Data Sheet'!B61,0) | D52: =IFERROR('Data Sheet'!C61,0) | E52: =IFERROR('Data Sheet'!D61,0) | F52: =IFERROR('Data Sheet'!E61,0) | G52: =IFERROR('Data Sheet'!F61,0) | H52: =IFERROR('Data Sheet'!G61,0) | I52: =IFERROR('Data Sheet'!H61,0) | J52: =IFERROR('Data Sheet'!I61,0) | ... L52: =IFERROR('Data Sheet'!K61,0)
B54: Fixex Assets Net Block | C54: =IFERROR('Data Sheet'!B62,0) | D54: =IFERROR('Data Sheet'!C62,0) | E54: =IFERROR('Data Sheet'!D62,0) | F54: =IFERROR('Data Sheet'!E62,0) | G54: =IFERROR('Data Sheet'!F62,0) | H54: =IFERROR('Data Sheet'!G62,0) | I54: =IFERROR('Data Sheet'!H62,0) | J54: =IFERROR('Data Sheet'!I62,0) | ... L54: =IFERROR('Data Sheet'!K62,0)
B55: Capital Work in Progress | C55: =IFERROR('Data Sheet'!B63,0) | D55: =IFERROR('Data Sheet'!C63,0) | E55: =IFERROR('Data Sheet'!D63,0) | F55: =IFERROR('Data Sheet'!E63,0) | G55: =IFERROR('Data Sheet'!F63,0) | H55: =IFERROR('Data Sheet'!G63,0) | I55: =IFERROR('Data Sheet'!H63,0) | J55: =IFERROR('Data Sheet'!I63,0) | ... L55: =IFERROR('Data Sheet'!K63,0)
B56: Investments | C56: =IFERROR('Data Sheet'!B64,0) | D56: =IFERROR('Data Sheet'!C64,0) | E56: =IFERROR('Data Sheet'!D64,0) | F56: =IFERROR('Data Sheet'!E64,0) | G56: =IFERROR('Data Sheet'!F64,0) | H56: =IFERROR('Data Sheet'!G64,0) | I56: =IFERROR('Data Sheet'!H64,0) | J56: =IFERROR('Data Sheet'!I64,0) | ... L56: =IFERROR('Data Sheet'!K64,0)
B57: Other Assets | C57: =IFERROR('Data Sheet'!B65-SUM('Data Sheet'!B67:B69),0) | D57: =IFERROR('Data Sheet'!C65-SUM('Data Sheet'!C67:C69),0) | E57: =IFERROR('Data Sheet'!D65-SUM('Data Sheet'!D67:D69),0) | F57: =IFERROR('Data Sheet'!E65-SUM('Data Sheet'!E67:E69),0) | G57: =IFERROR('Data Sheet'!F65-SUM('Data Sheet'!F67:F69),0) | H57: =IFERROR('Data Sheet'!G65-SUM('Data Sheet'!G67:G69),0) | I57: =IFERROR('Data Sheet'!H65-SUM('Data Sheet'!H67:H69),0) | J57: =IFERROR('Data Sheet'!I65-SUM('Data Sheet'!I67:I69),0) | ... L57: =IFERROR('Data Sheet'!K65-SUM('Data Sheet'!K67:K69),0)
B58: Total Non Current Assets | C58: =SUM(C54:C57) | D58: =SUM(D54:D57) | E58: =SUM(E54:E57) | F58: =SUM(F54:F57) | G58: =SUM(G54:G57) | H58: =SUM(H54:H57) | I58: =SUM(I54:I57) | J58: =SUM(J54:J57) | ... L58: =SUM(L54:L57)
B60: Receivables | C60: =IFERROR('Data Sheet'!B67,0) | D60: =IFERROR('Data Sheet'!C67,0) | E60: =IFERROR('Data Sheet'!D67,0) | F60: =IFERROR('Data Sheet'!E67,0) | G60: =IFERROR('Data Sheet'!F67,0) | H60: =IFERROR('Data Sheet'!G67,0) | I60: =IFERROR('Data Sheet'!H67,0) | J60: =IFERROR('Data Sheet'!I67,0) | ... L60: =IFERROR('Data Sheet'!K67,0)
B61: Inventory | C61: =IFERROR('Data Sheet'!B68,0) | D61: =IFERROR('Data Sheet'!C68,0) | E61: =IFERROR('Data Sheet'!D68,0) | F61: =IFERROR('Data Sheet'!E68,0) | G61: =IFERROR('Data Sheet'!F68,0) | H61: =IFERROR('Data Sheet'!G68,0) | I61: =IFERROR('Data Sheet'!H68,0) | J61: =IFERROR('Data Sheet'!I68,0) | ... L61: =IFERROR('Data Sheet'!K68,0)
B62: Cash & Bank | C62: =IFERROR('Data Sheet'!B69,0) | D62: =IFERROR('Data Sheet'!C69,0) | E62: =IFERROR('Data Sheet'!D69,0) | F62: =IFERROR('Data Sheet'!E69,0) | G62: =IFERROR('Data Sheet'!F69,0) | H62: =IFERROR('Data Sheet'!G69,0) | I62: =IFERROR('Data Sheet'!H69,0) | J62: =IFERROR('Data Sheet'!I69,0) | ... L62: =IFERROR('Data Sheet'!K69,0)
B63: Total Current Assets | C63: =IFERROR(SUM(C60:C62),0) | D63: =IFERROR(SUM(D60:D62),0) | E63: =IFERROR(SUM(E60:E62),0) | F63: =IFERROR(SUM(F60:F62),0) | G63: =IFERROR(SUM(G60:G62),0) | H63: =IFERROR(SUM(H60:H62),0) | I63: =IFERROR(SUM(I60:I62),0) | J63: =IFERROR(SUM(J60:J62),0) | ... L63: =IFERROR(SUM(L60:L62),0)
B65: Total Assets | C65: =IFERROR(C63+C58,0) | D65: =IFERROR(D63+D58,0) | E65: =IFERROR(E63+E58,0) | F65: =IFERROR(F63+F58,0) | G65: =IFERROR(G63+G58,0) | H65: =IFERROR(H63+H58,0) | I65: =IFERROR(I63+I58,0) | J65: =IFERROR(J63+J58,0) | ... L65: =IFERROR(L63+L58,0)
B67: Check | C67: =C65=C52 | D67: =D65=D52 | E67: =E65=E52 | F67: =F65=F52 | G67: =G65=G52 | H67: =H65=H52 | I67: =I65=I52 | J67: =J65=J52 | ... L67: =L65=L52
A69: # | B69: Cash Flow Statements
B70: Operating Activities
B71: Profit from operations | C71: =IFERROR('Cash flow Data'!E4,0) | D71: =IFERROR('Cash flow Data'!F4,0) | E71: =IFERROR('Cash flow Data'!G4,0) | F71: =IFERROR('Cash flow Data'!H4,0) | G71: =IFERROR('Cash flow Data'!I4,0) | H71: =IFERROR('Cash flow Data'!J4,0) | I71: =IFERROR('Cash flow Data'!K4,0) | J71: =IFERROR('Cash flow Data'!L4,0) | ... L71: =IFERROR('Cash flow Data'!N4,0)
B72: Receivables | C72: =IFERROR('Cash flow Data'!E5,0) | D72: =IFERROR('Cash flow Data'!F5,0) | E72: =IFERROR('Cash flow Data'!G5,0) | F72: =IFERROR('Cash flow Data'!H5,0) | G72: =IFERROR('Cash flow Data'!I5,0) | H72: =IFERROR('Cash flow Data'!J5,0) | I72: =IFERROR('Cash flow Data'!K5,0) | J72: =IFERROR('Cash flow Data'!L5,0) | ... L72: =IFERROR('Cash flow Data'!N5,0)
B73: Inventory | C73: =IFERROR('Cash flow Data'!E6,0) | D73: =IFERROR('Cash flow Data'!F6,0) | E73: =IFERROR('Cash flow Data'!G6,0) | F73: =IFERROR('Cash flow Data'!H6,0) | G73: =IFERROR('Cash flow Data'!I6,0) | H73: =IFERROR('Cash flow Data'!J6,0) | I73: =IFERROR('Cash flow Data'!K6,0) | J73: =IFERROR('Cash flow Data'!L6,0) | ... L73: =IFERROR('Cash flow Data'!N6,0)
B74: Payables | C74: =IFERROR('Cash flow Data'!E7,0) | D74: =IFERROR('Cash flow Data'!F7,0) | E74: =IFERROR('Cash flow Data'!G7,0) | F74: =IFERROR('Cash flow Data'!H7,0) | G74: =IFERROR('Cash flow Data'!I7,0) | H74: =IFERROR('Cash flow Data'!J7,0) | I74: =IFERROR('Cash flow Data'!K7,0) | J74: =IFERROR('Cash flow Data'!L7,0) | ... L74: =IFERROR('Cash flow Data'!N7,0)
B75: Loans Advances | C75: =IFERROR('Cash flow Data'!E8,0) | D75: =IFERROR('Cash flow Data'!F8,0) | E75: =IFERROR('Cash flow Data'!G8,0) | F75: =IFERROR('Cash flow Data'!H8,0) | G75: =IFERROR('Cash flow Data'!I8,0) | H75: =IFERROR('Cash flow Data'!J8,0) | I75: =IFERROR('Cash flow Data'!K8,0) | J75: =IFERROR('Cash flow Data'!L8,0) | ... L75: =IFERROR('Cash flow Data'!N8,0)
B76: Other WC items | C76: =IFERROR('Cash flow Data'!E9,0) | D76: =IFERROR('Cash flow Data'!F9,0) | E76: =IFERROR('Cash flow Data'!G9,0) | F76: =IFERROR('Cash flow Data'!H9,0) | G76: =IFERROR('Cash flow Data'!I9,0) | H76: =IFERROR('Cash flow Data'!J9,0) | I76: =IFERROR('Cash flow Data'!K9,0) | J76: =IFERROR('Cash flow Data'!L9,0) | ... L76: =IFERROR('Cash flow Data'!N9,0)
B77: Working capital changes | C77: =IFERROR('Cash flow Data'!E10,0) | D77: =IFERROR('Cash flow Data'!F10,0) | E77: =IFERROR('Cash flow Data'!G10,0) | F77: =IFERROR('Cash flow Data'!H10,0) | G77: =IFERROR('Cash flow Data'!I10,0) | H77: =IFERROR('Cash flow Data'!J10,0) | I77: =IFERROR('Cash flow Data'!K10,0) | J77: =IFERROR('Cash flow Data'!L10,0) | ... L77: =IFERROR('Cash flow Data'!N10,0)
B78: Direct taxes | C78: =IFERROR('Cash flow Data'!E11,0) | D78: =IFERROR('Cash flow Data'!F11,0) | E78: =IFERROR('Cash flow Data'!G11,0) | F78: =IFERROR('Cash flow Data'!H11,0) | G78: =IFERROR('Cash flow Data'!I11,0) | H78: =IFERROR('Cash flow Data'!J11,0) | I78: =IFERROR('Cash flow Data'!K11,0) | J78: =IFERROR('Cash flow Data'!L11,0) | ... L78: =IFERROR('Cash flow Data'!N11,0)
B79: Cash From Operating Activities | C79: =SUM(C71:C78) | D79: =SUM(D71:D78) | E79: =SUM(E71:E78) | F79: =SUM(F71:F78) | G79: =SUM(G71:G78) | H79: =SUM(H71:H78) | I79: =SUM(I71:I78) | J79: =SUM(J71:J78) | ... L79: =SUM(L71:L78)
B81: Investing Activities
B82: Fixed assets purchased | C82: =IFERROR('Cash flow Data'!E13,0) | D82: =IFERROR('Cash flow Data'!F13,0) | E82: =IFERROR('Cash flow Data'!G13,0) | F82: =IFERROR('Cash flow Data'!H13,0) | G82: =IFERROR('Cash flow Data'!I13,0) | H82: =IFERROR('Cash flow Data'!J13,0) | I82: =IFERROR('Cash flow Data'!K13,0) | J82: =IFERROR('Cash flow Data'!L13,0) | ... L82: =IFERROR('Cash flow Data'!N13,0)
B83: Fixed assets sold | C83: =IFERROR('Cash flow Data'!E14,0) | D83: =IFERROR('Cash flow Data'!F14,0) | E83: =IFERROR('Cash flow Data'!G14,0) | F83: =IFERROR('Cash flow Data'!H14,0) | G83: =IFERROR('Cash flow Data'!I14,0) | H83: =IFERROR('Cash flow Data'!J14,0) | I83: =IFERROR('Cash flow Data'!K14,0) | J83: =IFERROR('Cash flow Data'!L14,0) | ... L83: =IFERROR('Cash flow Data'!N14,0)
B84: Investments purchased | C84: =IFERROR('Cash flow Data'!E15,0) | D84: =IFERROR('Cash flow Data'!F15,0) | E84: =IFERROR('Cash flow Data'!G15,0) | F84: =IFERROR('Cash flow Data'!H15,0) | G84: =IFERROR('Cash flow Data'!I15,0) | H84: =IFERROR('Cash flow Data'!J15,0) | I84: =IFERROR('Cash flow Data'!K15,0) | J84: =IFERROR('Cash flow Data'!L15,0) | ... L84: =IFERROR('Cash flow Data'!N15,0)
B85: Investments sold | C85: =IFERROR('Cash flow Data'!E16,0) | D85: =IFERROR('Cash flow Data'!F16,0) | E85: =IFERROR('Cash flow Data'!G16,0) | F85: =IFERROR('Cash flow Data'!H16,0) | G85: =IFERROR('Cash flow Data'!I16,0) | H85: =IFERROR('Cash flow Data'!J16,0) | I85: =IFERROR('Cash flow Data'!K16,0) | J85: =IFERROR('Cash flow Data'!L16,0) | ... L85: =IFERROR('Cash flow Data'!N16,0)
B86: Interest received | C86: =IFERROR('Cash flow Data'!E17,0) | D86: =IFERROR('Cash flow Data'!F17,0) | E86: =IFERROR('Cash flow Data'!G17,0) | F86: =IFERROR('Cash flow Data'!H17,0) | G86: =IFERROR('Cash flow Data'!I17,0) | H86: =IFERROR('Cash flow Data'!J17,0) | I86: =IFERROR('Cash flow Data'!K17,0) | J86: =IFERROR('Cash flow Data'!L17,0) | ... L86: =IFERROR('Cash flow Data'!N17,0)
B87: Dividends received | C87: =IFERROR('Cash flow Data'!E18,0) | D87: =IFERROR('Cash flow Data'!F18,0) | E87: =IFERROR('Cash flow Data'!G18,0) | F87: =IFERROR('Cash flow Data'!H18,0) | G87: =IFERROR('Cash flow Data'!I18,0) | H87: =IFERROR('Cash flow Data'!J18,0) | I87: =IFERROR('Cash flow Data'!K18,0) | J87: =IFERROR('Cash flow Data'!L18,0) | ... L87: =IFERROR('Cash flow Data'!N18,0)
B88: Invest in subsidiaries | C88: =IFERROR('Cash flow Data'!E19,0) | D88: =IFERROR('Cash flow Data'!F19,0) | E88: =IFERROR('Cash flow Data'!G19,0) | F88: =IFERROR('Cash flow Data'!H19,0) | G88: =IFERROR('Cash flow Data'!I19,0) | H88: =IFERROR('Cash flow Data'!J19,0) | I88: =IFERROR('Cash flow Data'!K19,0) | J88: =IFERROR('Cash flow Data'!L19,0) | ... L88: =IFERROR('Cash flow Data'!N19,0)
B89: Investment in group cos | C89: =IFERROR('Cash flow Data'!E20,0) | D89: =IFERROR('Cash flow Data'!F20,0) | E89: =IFERROR('Cash flow Data'!G20,0) | F89: =IFERROR('Cash flow Data'!H20,0) | G89: =IFERROR('Cash flow Data'!I20,0) | H89: =IFERROR('Cash flow Data'!J20,0) | I89: =IFERROR('Cash flow Data'!K20,0) | J89: =IFERROR('Cash flow Data'!L20,0) | ... L89: =IFERROR('Cash flow Data'!N20,0)
B90: Redemp n Canc of Shares | C90: =IFERROR('Cash flow Data'!E21,0) | D90: =IFERROR('Cash flow Data'!F21,0) | E90: =IFERROR('Cash flow Data'!G21,0) | F90: =IFERROR('Cash flow Data'!H21,0) | G90: =IFERROR('Cash flow Data'!I21,0) | H90: =IFERROR('Cash flow Data'!J21,0) | I90: =IFERROR('Cash flow Data'!K21,0) | J90: =IFERROR('Cash flow Data'!L21,0) | ... L90: =IFERROR('Cash flow Data'!N21,0)
B91: Acquisition of companies | C91: =IFERROR('Cash flow Data'!E22,0) | D91: =IFERROR('Cash flow Data'!F22,0) | E91: =IFERROR('Cash flow Data'!G22,0) | F91: =IFERROR('Cash flow Data'!H22,0) | G91: =IFERROR('Cash flow Data'!I22,0) | H91: =IFERROR('Cash flow Data'!J22,0) | I91: =IFERROR('Cash flow Data'!K22,0) | J91: =IFERROR('Cash flow Data'!L22,0) | ... L91: =IFERROR('Cash flow Data'!N22,0)
B92: Inter corporate deposits | C92: =IFERROR('Cash flow Data'!E23,0) | D92: =IFERROR('Cash flow Data'!F23,0) | E92: =IFERROR('Cash flow Data'!G23,0) | F92: =IFERROR('Cash flow Data'!H23,0) | G92: =IFERROR('Cash flow Data'!I23,0) | H92: =IFERROR('Cash flow Data'!J23,0) | I92: =IFERROR('Cash flow Data'!K23,0) | J92: =IFERROR('Cash flow Data'!L23,0) | ... L92: =IFERROR('Cash flow Data'!N23,0)
B93: Other investing items | C93: =IFERROR('Cash flow Data'!E24,0) | D93: =IFERROR('Cash flow Data'!F24,0) | E93: =IFERROR('Cash flow Data'!G24,0) | F93: =IFERROR('Cash flow Data'!H24,0) | G93: =IFERROR('Cash flow Data'!I24,0) | H93: =IFERROR('Cash flow Data'!J24,0) | I93: =IFERROR('Cash flow Data'!K24,0) | J93: =IFERROR('Cash flow Data'!L24,0) | ... L93: =IFERROR('Cash flow Data'!N24,0)
B94: Cash From Investing Activities | C94: =SUM(C82:C93) | D94: =SUM(D82:D93) | E94: =SUM(E82:E93) | F94: =SUM(F82:F93) | G94: =SUM(G82:G93) | H94: =SUM(H82:H93) | I94: =SUM(I82:I93) | J94: =SUM(J82:J93) | ... L94: =SUM(L82:L93)
B96: Financing Activity
B97: Proceeds from shares | C97: =IFERROR('Cash flow Data'!C26,0) | D97: =IFERROR('Cash flow Data'!D26,0) | E97: =IFERROR('Cash flow Data'!E26,0) | F97: =IFERROR('Cash flow Data'!F26,0) | G97: =IFERROR('Cash flow Data'!G26,0) | H97: =IFERROR('Cash flow Data'!H26,0) | I97: =IFERROR('Cash flow Data'!I26,0) | J97: =IFERROR('Cash flow Data'!J26,0) | ... L97: =IFERROR('Cash flow Data'!L26,0)
B98: Redemption of debentures | C98: =IFERROR('Cash flow Data'!C27,0) | D98: =IFERROR('Cash flow Data'!D27,0) | E98: =IFERROR('Cash flow Data'!E27,0) | F98: =IFERROR('Cash flow Data'!F27,0) | G98: =IFERROR('Cash flow Data'!G27,0) | H98: =IFERROR('Cash flow Data'!H27,0) | I98: =IFERROR('Cash flow Data'!I27,0) | J98: =IFERROR('Cash flow Data'!J27,0) | ... L98: =IFERROR('Cash flow Data'!L27,0)
B99: Proceeds from borrowings | C99: =IFERROR('Cash flow Data'!C28,0) | D99: =IFERROR('Cash flow Data'!D28,0) | E99: =IFERROR('Cash flow Data'!E28,0) | F99: =IFERROR('Cash flow Data'!F28,0) | G99: =IFERROR('Cash flow Data'!G28,0) | H99: =IFERROR('Cash flow Data'!H28,0) | I99: =IFERROR('Cash flow Data'!I28,0) | J99: =IFERROR('Cash flow Data'!J28,0) | ... L99: =IFERROR('Cash flow Data'!L28,0)
B100: Repayment of borrowings | C100: =IFERROR('Cash flow Data'!C29,0) | D100: =IFERROR('Cash flow Data'!D29,0) | E100: =IFERROR('Cash flow Data'!E29,0) | F100: =IFERROR('Cash flow Data'!F29,0) | G100: =IFERROR('Cash flow Data'!G29,0) | H100: =IFERROR('Cash flow Data'!H29,0) | I100: =IFERROR('Cash flow Data'!I29,0) | J100: =IFERROR('Cash flow Data'!J29,0) | ... L100: =IFERROR('Cash flow Data'!L29,0)
B101: Interest paid fin | C101: =IFERROR('Cash flow Data'!C30,0) | D101: =IFERROR('Cash flow Data'!D30,0) | E101: =IFERROR('Cash flow Data'!E30,0) | F101: =IFERROR('Cash flow Data'!F30,0) | G101: =IFERROR('Cash flow Data'!G30,0) | H101: =IFERROR('Cash flow Data'!H30,0) | I101: =IFERROR('Cash flow Data'!I30,0) | J101: =IFERROR('Cash flow Data'!J30,0) | ... L101: =IFERROR('Cash flow Data'!L30,0)
B102: Dividends paid | C102: =IFERROR('Cash flow Data'!C31,0) | D102: =IFERROR('Cash flow Data'!D31,0) | E102: =IFERROR('Cash flow Data'!E31,0) | F102: =IFERROR('Cash flow Data'!F31,0) | G102: =IFERROR('Cash flow Data'!G31,0) | H102: =IFERROR('Cash flow Data'!H31,0) | I102: =IFERROR('Cash flow Data'!I31,0) | J102: =IFERROR('Cash flow Data'!J31,0) | ... L102: =IFERROR('Cash flow Data'!L31,0)
B103: Financial liabilities | C103: =IFERROR('Cash flow Data'!C32,0) | D103: =IFERROR('Cash flow Data'!D32,0) | E103: =IFERROR('Cash flow Data'!E32,0) | F103: =IFERROR('Cash flow Data'!F32,0) | G103: =IFERROR('Cash flow Data'!G32,0) | H103: =IFERROR('Cash flow Data'!H32,0) | I103: =IFERROR('Cash flow Data'!I32,0) | J103: =IFERROR('Cash flow Data'!J32,0) | ... L103: =IFERROR('Cash flow Data'!L32,0)
B104: Other financing items | C104: =IFERROR('Cash flow Data'!C33,0) | D104: =IFERROR('Cash flow Data'!D33,0) | E104: =IFERROR('Cash flow Data'!E33,0) | F104: =IFERROR('Cash flow Data'!F33,0) | G104: =IFERROR('Cash flow Data'!G33,0) | H104: =IFERROR('Cash flow Data'!H33,0) | I104: =IFERROR('Cash flow Data'!I33,0) | J104: =IFERROR('Cash flow Data'!J33,0) | ... L104: =IFERROR('Cash flow Data'!L33,0)
B105: Cash From Financing Activities | C105: =SUM(C97:C104) | D105: =SUM(D97:D104) | E105: =SUM(E97:E104) | F105: =SUM(F97:F104) | G105: =SUM(G97:G104) | H105: =SUM(H97:H104) | I105: =SUM(I97:I104) | J105: =SUM(J97:J104) | ... L105: =SUM(L97:L104)
B107: Net Cash Flow | C107: =IFERROR(C79+C94+C105,0) | D107: =IFERROR(D79+D94+D105,0) | E107: =IFERROR(E79+E94+E105,0) | F107: =IFERROR(F79+F94+F105,0) | G107: =IFERROR(G79+G94+G105,0) | H107: =IFERROR(H79+H94+H105,0) | I107: =IFERROR(I79+I94+I105,0) | J107: =IFERROR(J79+J94+J105,0) | ... L107: =IFERROR(L79+L94+L105,0)

Sheet Data Sheet
A1: COMPANY NAME | B1: NESTLE INDIA LTD | E1: =IF(B2<>B3, "A NEW VERSION OF THE WORKSHEET IS AVAILABLE", "")
A2: LATEST VERSION | B2: 2.1 | E2: PLEASE DO NOT MAKE ANY CHANGES TO THIS SHEET
A3: CURRENT VERSION | B3: 2.1
A5: META
A6: Number of shares | B6: =IF(B9>0, B9/B8, 0)
A7: Face Value | B7: 1
A8: Current Price | B8: 1246.9
A9: Market Capitalization | B9: 240441.51
A15: PROFIT & LOSS
A16: Report Date | B16: 42735 | C16: 43100 | D16: 43465 | E16: 43830 | F16: 44196 | G16: 44561 | H16: 44926 | I16: 45291 | J16: 45382 | K16: 45747
A17: Sales | B17: 9141.34 | C17: 10009.6 | D17: 11292.27 | E17: 12368.9 | F17: 13350.03 | G17: 14740.59 | H17: 16896.96 | I17: 19126.3 | J17: 24393.89 | K17: 20201.56
A18: Raw Material Cost | B18: 3227.26 | C18: 3696.99 | D18: 3829.22 | E18: 4520.91 | F18: 4901.74 | G18: 5301.26 | H18: 6660.42 | I18: 8472.72 | J18: 9201.11 | K18: 7646.63
A19: Change in Inventory | B19: 7.66 | C19: 79.56 | D19: 6.01 | E19: 144.19 | F19: 69.33 | G19: 67.59 | H19: 250.27 | I19: 40.01 | J19: 45.68 | K19: 139.66
A20: Power and Fuel | B20: 232.79 | C20: 288.44 | D20: 344.18 | E20: 340.53 | F20: 313.68 | G20: 408.06 | H20: 572.61 | J20: 674.83 | K20: 536.65
A21: Other Mfr. Exp | B21: 850.85 | C21: 897.84 | D21: 949.86 | E21: 1028.55 | F21: 1040.36 | G21: 1349.48 | H21: 1603.48 | J21: 1935.4 | K21: 1579.8
A22: Employee Cost | B22: 901.57 | C22: 1017.45 | D22: 1124.15 | E22: 1258.17 | F22: 1500.95 | G22: 1529.94 | H22: 1635.46 | I22: 1849.18 | J22: 2336.06 | K22: 2023.71
A23: Selling and admin | B23: 1751.78 | C23: 1823.98 | D23: 2145.82 | E23: 2226.13 | F23: 2246.9 | G23: 2902.12 | H23: 3192.15 | J23: 4837.58 | K23: 4121.66
A24: Other Expenses | B24: 334.91 | C24: 267.93 | D24: 287.4 | E24: 212.92 | F24: 214.23 | G24: -245.08 | H24: -223.18 | I24: 4373.42 | J24: -388.53 | K24: -338.56
A25: Other Income | B25: 140.12 | C25: 176.92 | D25: 258.92 | E25: 246.88 | F25: 145.85 | G25: -112.38 | H25: 107.26 | I25: 115.5 | J25: 158.99 | K25: 352.06
A26: Depreciation | B26: 353.67 | C26: 342.25 | D26: 335.67 | E26: 370.15 | F26: 370.38 | G26: 391.02 | H26: 403.01 | I26: 428.91 | J26: 567.75 | K26: 539.92
A27: Interest | B27: 90.91 | C27: 91.9 | D27: 111.95 | E27: 129.12 | F27: 164.18 | G27: 201.68 | H27: 154.57 | I27: 119.29 | J27: 145.49 | K27: 136
A28: Profit before tax | B28: 1545.38 | C28: 1839.3 | D28: 2428.95 | E28: 2673.49 | F28: 2812.79 | G28: 2857.32 | H28: 3255.97 | I28: 4038.29 | J28: 5288.87 | K28: 4447.47
A29: Tax | B29: 544.02 | C29: 614.11 | D29: 822.02 | E29: 705.05 | F29: 730.36 | G29: 738.91 | H29: 865.45 | I29: 1039.62 | J29: 1356.03 | K29: 1132.97
A30: Net profit | B30: 1001.36 | C30: 1225.19 | D30: 1606.93 | E30: 1968.44 | F30: 2082.43 | G30: 2118.41 | H30: 2390.52 | I30: 2998.67 | J30: 3932.84 | K30: 3314.5
A31: Dividend Amount | B31: 607.45 | C31: 829.21 | D31: 1108.83 | E31: 3297.56 | F31: 1928.4 | G31: 1928.4 | H31: 2121.24 | I31: 1677.71 | J31: 3104.72 | K31: 2603.34
A40: Quarters
A41: Report Date | B41: 45107 | C41: 45199 | D41: 45291 | E41: 45382 | F41: 45473 | G41: 45565 | H41: 45657 | I41: 45747 | J41: 45838 | K41: 45930
A42: Sales | B42: 4658.53 | C42: 5036.82 | D42: 4600.42 | E42: 5267.59 | F42: 4813.95 | G42: 5104 | H42: 4779.73 | I42: 5503.88 | J42: 5096.16 | K42: 5643.61
A43: Expenses | B43: 3603.01 | C43: 3811.95 | D43: 3505.3 | E43: 3917.54 | F43: 3699.62 | G43: 3936.27 | H43: 3677.04 | I43: 4114.92 | J43: 3995.9 | K43: 4406.97
A44: Other Income | B44: 23.95 | C44: 139.69 | D44: -77 | E44: 36.83 | F44: 39.12 | G44: 297.68 | H44: 4.44 | I44: 8.44 | J44: 4.04 | K44: 1.64
A45: Depreciation | B45: 107.36 | C45: 111.16 | D45: 108.69 | E45: 110.1 | F45: 112.71 | G45: 121.6 | H45: 150.27 | I45: 155.34 | J45: 156.94 | K45: 163.35
A46: Interest | B46: 32.78 | C46: 31.38 | D46: 22.95 | E46: 26.2 | F46: 31.68 | G46: 32.22 | H46: 34.6 | I46: 37.5 | J46: 46.89 | K46: 46.41
A47: Profit before tax | B47: 939.33 | C47: 1222.02 | D47: 886.48 | E47: 1250.58 | F47: 1009.06 | G47: 1311.59 | H47: 922.26 | I47: 1204.56 | J47: 900.47 | K47: 1028.52
A48: Tax | B48: 240.99 | C48: 313.94 | D48: 230.87 | E48: 316.41 | F48: 262.46 | G48: 325.23 | H48: 226.13 | I48: 319.15 | J48: 241.24 | K48: 275.32
A49: Net profit | B49: 698.34 | C49: 908.08 | D49: 655.61 | E49: 934.17 | F49: 746.6 | G49: 986.36 | H49: 696.13 | I49: 885.41 | J49: 659.23 | K49: 753.2
A50: Operating Profit | B50: 1055.52 | C50: 1224.87 | D50: 1095.12 | E50: 1350.05 | F50: 1114.33 | G50: 1167.73 | H50: 1102.69 | I50: 1388.96 | J50: 1100.26 | K50: 1236.64
A55: BALANCE SHEET
A56: Report Date | B56: 42735 | C56: 43100 | D56: 43465 | E56: 43830 | F56: 44196 | G56: 44561 | H56: 44926 | I56: 45291 | J56: 45382 | K56: 45747
A57: Equity Share Capital | B57: 96.42 | C57: 96.42 | D57: 96.42 | E57: 96.42 | F57: 96.42 | G57: 96.42 | H57: 96.42 | I57: 96.42 | J57: 96.42 | K57: 96.42
A58: Reserves | B58: 3185.91 | C58: 3324.17 | D58: 3577.32 | E58: 1822.45 | F58: 1922.92 | G58: 1849.96 | H58: 2362.75 | I58: 2362.75 | J58: 3244.47 | K58: 4020.73
A59: Borrowings | B59: 33.15 | C59: 35.14 | D59: 35.14 | E59: 188.94 | F59: 147.49 | G59: 266.46 | H59: 270.52 | I59: 270.52 | J59: 344.53 | K59: 1166.85
A60: Other Liabilities | B60: 3494.98 | C60: 3906.86 | D60: 4379.2 | E60: 5065.13 | F60: 5732.9 | G60: 6021.29 | H60: 6249.05 | I60: 6249.05 | J60: 6837.64 | K60: 7039.89
A61: Total | B61: 6810.46 | C61: 7362.59 | D61: 8088.08 | E61: 7172.94 | F61: 7899.73 | G61: 8234.13 | H61: 8978.74 | I61: 8978.74 | J61: 10523.06 | K61: 12323.89
A62: Net Block | B62: 2730.14 | C62: 2616.18 | D62: 2400.62 | E62: 2341.45 | F62: 2179.41 | G62: 2994.67 | H62: 3043.7 | I62: 3043.7 | J62: 3460.25 | K62: 5473.61
A63: Capital Work in Progress | B63: 188.17 | C63: 94.16 | D63: 105.2 | E63: 143.3 | F63: 638.58 | G63: 246.23 | H63: 358.36 | I63: 358.36 | J63: 1741.71 | K63: 1172.56
A64: Investments | B64: 1755.66 | C64: 1978.87 | D64: 2658.49 | E64: 1751.05 | F64: 1463.77 | G64: 773.98 | H64: 777.54 | I64: 777.54 | J64: 463.87 | K64: 705.6
A65: Other Assets | B65: 2136.49 | C65: 2673.38 | D65: 2923.77 | E65: 2937.14 | F65: 3617.97 | G65: 4219.25 | H65: 4799.14 | I65: 4799.14 | J65: 4857.23 | K65: 4972.12
A66: Total | B66: 6810.46 | C66: 7362.59 | D66: 8088.08 | E66: 7172.94 | F66: 7899.73 | G66: 8234.13 | H66: 8978.74 | I66: 8978.74 | J66: 10523.06 | K66: 12323.89
A67: Receivables | B67: 97.93 | C67: 88.97 | D67: 124.59 | E67: 124.33 | F67: 164.93 | G67: 165.97 | H67: 191.89 | I67: 191.89 | J67: 300.46 | K67: 363.15
... A69: Cash & Bank | B69: 880 | C69: 1457.42 | D69: 1610.06 | E69: 1308.05 | F69: 1769.87 | G69: 735.41 | H69: 945.55 | I69: 945.55 | J69: 778.85 | K69: 95.65
A70: No. of Equity Shares | B70: 96415716 | C70: 96415716 | D70: 96415716 | E70: 96415716 | F70: 96415716 | G70: 96415716 | H70: 96415716 | J70: 964157160 | K70: 964157160
A71: New Bonus Shares
A72: Face value | B72: 10 | C72: 10 | D72: 10 | E72: 10 | F72: 10 | G72: 10 | H72: 10 | I72: 10 | J72: 1 | K72: 1
A80: CASH FLOW:
A81: Report Date | B81: 42735 | C81: 43100 | D81: 43465 | E81: 43830 | F81: 44196 | G81: 44561 | H81: 44926 | I81: 45291 | J81: 45382 | K81: 45747
A82: Cash from Operating Activity | B82: 1465.91 | C82: 1817.79 | D82: 2052.45 | E82: 2295.25 | F82: 2454.48 | G82: 2236 | H82: 2737.43 | I82: 3392.19 | J82: 4174.79 | K82: 2936.35
A83: Cash from Investing Activity | B83: -125.9 | C83: -130.56 | D83: -52.41 | E83: 82.99 | F83: -321.46 | G83: -1920.33 | H83: -391.73 | I83: -926.99 | J83: -1237.42 | K83: -1810.9
A84: Cash from Financing Activity | B84: -665.61 | C84: -996.62 | D84: -1317.42 | E84: -3601.53 | F84: -1955.89 | G84: -2019.97 | H84: -2122.74 | I84: -2436.47 | J84: -3134.92 | K84: -1848.12
A85: Net Cash Flow | B85: 674.4 | C85: 690.61 | D85: 682.62 | E85: -1223.29 | F85: 177.13 | G85: -1704.3 | H85: 222.96 | I85: 28.73 | J85: -197.55 | K85: -722.67
A90: PRICE: | B90: 301.42 | C90: 393.55 | D90: 554.24 | E90: 739.27 | F90: 919.51 | G90: 985.29 | H90: 980.3 | I90: 1329.02 | J90: 1311.18 | K90: 1125.38
A92: DERIVED:
A93: Adjusted Equity Shares in Cr | B93: 192.8 | C93: 192.8 | D93: 192.8 | E93: 192.8 | F93: 192.8 | G93: 192.8 | H93: 192.8 | I93: 192.8 | J93: 192.83 | K93: 192.83

Sheet Cash flow Data
C2: 40969 | D2: 41334 | E2: 41699 | F2: 42064 | G2: 42430 | H2: 42795 | I2: 43160 | J2: 43525 | K2: 43891 | L2: 44256 | M2: 44621 | N2: 44986
B3: Cash from Operating Activity - | C3: 18384 | D3: 22163 | E3: 36151 | F3: 35531 | G3: 37900 | H3: 30199 | I3: 23857 | J3: 18891 | K3: 26633 | L3: 29001 | M3: 14283 | N3: 35388
B4: Profit from operations | C4: 22432 | D4: 24406 | E4: 36303 | F4: 43397 | G4: 38626 | H4: 28840 | I4: 33312 | J4: 28771 | K4: 23352 | L4: 31198 | M4: 26943 | N4: 41694
B5: Receivables | C5: -6659 | D5: -5177 | E5: 445 | F5: -3179 | G5: -2223 | H5: -4152 | I5: -10688 | J5: -9109 | K5: 9950 | L5: -5505 | M5: 185 | N5: -2213
B6: Inventory | C6: -2719 | D6: -2656 | E6: -2853 | F6: -3692 | G6: -5743 | H6: -6621 | I6: -3560 | J6: 2069 | K6: 2326 | L6: 3814 | M6: 472 | N6: -5665
B7: Payables | C7: 5867 | D7: 8132 | E7: 4694 | F7: 3598 | G7: 3947 | H7: 9301 | I7: 7320 | J7: -4692 | K7: -8085 | L7: 5748 | M7: -7012 | N7: 6945
B8: Loans Advances | C8: 0 | D8: 0 | E8: 0 | F8: 0 | G8: -520 | H8: 0 | I8: 0 | J8: 0 | K8: 0 | L8: 0 | M8: 0 | N8: 0
B9: Other WC items | C9: 1231 | D9: -303 | E9: 1870 | F9: -398 | G9: 5852 | H9: 4727 | I9: 494 | J9: 4512 | K9: 875 | L9: -4150 | M9: -4396 | N9: -2194
B10: Working capital changes | C10: -2280 | D10: -3 | E10: 4157 | F10: -3672 | G10: 1313 | H10: 3254 | I10: -6434 | J10: -7221 | K10: 5065 | L10: -93 | M10: -10750 | N10: -3127
B11: Direct taxes | C11: -1768 | D11: -2240 | E11: -4308 | F11: -4194 | G11: -2040 | H11: -1895 | I11: -3021 | J11: -2659 | K11: -1785 | L11: -2105 | M11: -1910 | N11: -3179
B12: Cash from Investing Activity - | C12: -19464 | D12: -22969 | E12: -27991 | F12: -36232 | G12: -36694 | H12: -39571 | I12: -25139 | J12: -20878 | K12: -33115 | L12: -25672 | M12: -4444 | N12: -15417
B13: Fixed assets purchased | C13: -13876 | D13: -18863 | E13: -26975 | F13: -31962 | G13: -31503 | H13: -16072 | I13: -35079 | J13: -35304 | K13: -29702 | L13: -20205 | M13: -15168 | N13: -19230
B14: Fixed assets sold | C14: 93 | D14: 37 | E14: 50 | F14: 74 | G14: 59 | H14: 53 | I14: 30 | J14: 67 | K14: 171 | L14: 351 | M14: 230 | N14: 285
... B34: Net Cash Flow | C34: 5488 | D34: -2499 | E34: 4277 | F34: 4500 | G34: -2589 | H34: -3167 | I34: 730 | J34: 6843 | K34: -3092 | L34: 13232 | M34: 6459 | N34: -6272
